Metadata-Version: 2.1
Name: scrooge-cache
Version: 0.1.1
Summary: Scrooge Cache
Home-page: https://github.com/marcelomoraes28/scrooge_cache
Author: Marcelo Moraes
Author-email: marcelomoraesjr28@gmail.com
License: UNKNOWN
Keywords: cache scrooge redis memcache
Platform: UNKNOWN
Classifier: Development Status :: 4 - Beta
Classifier: Programming Language :: Python
Classifier: License :: OSI Approved :: MIT License
Classifier: Topic :: Software Development :: Libraries :: Python Modules
Classifier: Programming Language :: Python :: 3.5
Classifier: Programming Language :: Python :: 3.6
Provides-Extra: test
Provides-Extra: ci
